a_sane_logger/__init__.py
a_sane_logger-0.3.dist-info/METADATA
a_sane_logger-0.3.dist-info/WHEEL
a_sane_logger-0.3.dist-info/top_level.txt
a_sane_logger-0.3.dist-info/zip-safe
a_sane_logger-0.3.dist-info/RECORD
