Metadata-Version: 2.1
Name: a_sane_logger
Version: 0.3
Summary: A simple logging configuration module
Author: Alex Popescu
Author-email: pop.alx@gmail.com
Keywords: logging
Classifier: Programming Language :: Python :: 3
Classifier: License :: OSI Approved :: MIT License
Classifier: Operating System :: OS Independent
Requires-Python: >=3.6
